setup.py
urlparse2/__init__.py
urlparse2/urlparse1.py
urlparse2/urlparse2.py
urlparse2.egg-info/PKG-INFO
urlparse2.egg-info/SOURCES.txt
urlparse2.egg-info/dependency_links.txt
urlparse2.egg-info/requires.txt
urlparse2.egg-info/top_level.txt